opensynth/__init__.py
opensynth/data_modules/__init__.py
opensynth/data_modules/lcl_data_module.py
opensynth/data_modules/streaming_data_module.py
opensynth/datasets/__init__.py
opensynth/datasets/datasets_utils.py
opensynth/datasets/low_carbon_london/__init__.py
opensynth/datasets/low_carbon_london/get_data.py
opensynth/datasets/low_carbon_london/preprocess_lcl.py
opensynth/datasets/low_carbon_london/split_households.py
opensynth/evaluation/__init__.py
opensynth/evaluation/privacy/__init__.py
opensynth/evaluation/privacy/generate_attack_data.py
opensynth/evaluation/privacy/membership_inference_attack.py
opensynth/evaluation/privacy/reconstruction_attack.py
opensynth/models/__init__.py
opensynth/models/energydiff/__init__.py
opensynth/models/energydiff/_diffusion_base.py
opensynth/models/energydiff/calibrate.py
opensynth/models/energydiff/diffusion.py
opensynth/models/energydiff/model.py
opensynth/models/energydiff/sampler.py
opensynth/models/faraday/__init__.py
opensynth/models/faraday/losses.py
opensynth/models/faraday/model.py
opensynth/models/faraday/vae_model.py
opensynth/models/faraday/gaussian_mixture/__init__.py
opensynth/models/faraday/gaussian_mixture/gmm_init.py
opensynth/models/faraday/gaussian_mixture/gmm_metrics.py
opensynth/models/faraday/gaussian_mixture/gmm_model.py
opensynth/models/faraday/gaussian_mixture/gmm_utils.py
opensynth_energy-1.0.0.dist-info/licenses/LICENSE
opensynth_energy-1.0.0.dist-info/METADATA
opensynth_energy-1.0.0.dist-info/WHEEL
opensynth_energy-1.0.0.dist-info/top_level.txt
opensynth_energy-1.0.0.dist-info/RECORD
