Metadata-Version: 2.4
Name: opensynth-energy
Version: 1.0.0
Summary: Opensynth is a library forsynthetic energy demand generation.
Author: Opensynth
Author-email: pypi@opensynth.energy
License: Apache 2.0
Classifier: Intended Audience :: Developers
Classifier: Operating System :: OS Independent
Classifier: Programming Language :: Python
Classifier: Programming Language :: Python :: 3
Classifier: Programming Language :: Python :: 3.11
License-File: LICENSE
Requires-Dist: wget>=3.2
Requires-Dist: tqdm>=4.66.4
Requires-Dist: numpy<=2.0.0
Requires-Dist: torch>=2.3.1
Requires-Dist: scikit-learn>=1.3.2
Requires-Dist: pytorch-lightning>=2.3.3
Requires-Dist: matplotlib>3.6.1
Requires-Dist: opacus>=1.4.1
Requires-Dist: seaborn>=0.13.2
Requires-Dist: torchmetrics>=1.4.1
Requires-Dist: pandas>=1.2
Requires-Dist: litdata==0.2.30
Requires-Dist: zstd==1.5.5.1
Requires-Dist: einops>=0.7.0
Requires-Dist: ema-pytorch==0.4.5
Dynamic: author
Dynamic: author-email
Dynamic: classifier
Dynamic: description
Dynamic: description-content-type
Dynamic: license
Dynamic: license-file
Dynamic: requires-dist
Dynamic: summary
